mitrecve/__init__.py
mitrecve/__main__.py
mitrecve/crawler.py
mitrecve/utility.py
mitrecve-1.1.1.dist-info/LICENSE
mitrecve-1.1.1.dist-info/METADATA
mitrecve-1.1.1.dist-info/WHEEL
mitrecve-1.1.1.dist-info/entry_points.txt
mitrecve-1.1.1.dist-info/top_level.txt
mitrecve-1.1.1.dist-info/RECORD
