Metadata-Version: 2.1
Name: mitrecve
Version: 1.1.1
Summary: Get all CVE corresponding to a specific keyword or list of keywords from the MITRE database.
Home-page: https://github.com/shadawck/mitrecve
Author: shadawck
Author-email: hug211mire@gmail.com
License: MIT
Platform: UNKNOWN
Classifier: License :: OSI Approved :: MIT License
Classifier: Programming Language :: Python :: 3
Classifier: Programming Language :: Python :: 3.7
Classifier: Programming Language :: Python :: 3.8
Classifier: Programming Language :: Python :: 3.9
Classifier: Programming Language :: Python :: 3.10
License-File: LICENSE
Requires-Dist: cssselect
Requires-Dist: docopt
Requires-Dist: lxml
Requires-Dist: requests
